CHANGES.txt
MANIFEST.in
README.rst
setup.py
repoze/__init__.py
repoze.who.plugins.vepauth.egg-info/PKG-INFO
repoze.who.plugins.vepauth.egg-info/SOURCES.txt
repoze.who.plugins.vepauth.egg-info/dependency_links.txt
repoze.who.plugins.vepauth.egg-info/namespace_packages.txt
repoze.who.plugins.vepauth.egg-info/not-zip-safe
repoze.who.plugins.vepauth.egg-info/requires.txt
repoze.who.plugins.vepauth.egg-info/top_level.txt
repoze/who/__init__.py
repoze/who/plugins/__init__.py
repoze/who/plugins/vepauth/__init__.py
repoze/who/plugins/vepauth/noncemanager.py
repoze/who/plugins/vepauth/tokenmanager.py
repoze/who/plugins/vepauth/utils.py
repoze/who/plugins/vepauth/tests/__init__.py
repoze/who/plugins/vepauth/tests/test_nonces.py
repoze/who/plugins/vepauth/tests/test_plugin.py
repoze/who/plugins/vepauth/tests/test_tokens.py
repoze/who/plugins/vepauth/tests/test_utils.py