Metadata-Version: 1.0
Name: repoze.who.plugins.vepauth
Version: 0.3.0
Summary: repoze.who.plugins.vepauth
Home-page: https://github.com/mozilla-services/repoze.who.plugins.vepauth
Author: Mozilla Services
Author-email: services-dev@mozilla.org
License: UNKNOWN
Keywords: authentication repoze browserid oauth
Platform: UNKNOWN
Classifier: Programming Language :: Python
